{
  "game": "Said It?",
  "days": [
    "2026-06-12",
    "2026-06-13",
    "2026-06-17",
    "2026-06-18",
    "2026-06-19",
    "2026-06-20",
    "2026-06-21",
    "2026-06-22",
    "2026-06-23",
    "2026-06-24",
    "2026-06-25",
    "2026-06-26",
    "2026-06-27",
    "2026-06-28",
    "2026-06-29",
    "2026-06-30"
  ],
  "note": "Manifest of published editions. The app loads daily/<local-date>.json; if that date isn't published yet, it falls back to the latest entry here.",
  "categories": {
    "sports": [
      "2026-06-17",
      "2026-06-18",
      "2026-06-19",
      "2026-06-20",
      "2026-06-30"
    ],
    "music": [
      "2026-06-17",
      "2026-06-18",
      "2026-06-19",
      "2026-06-20",
      "2026-06-22",
      "2026-06-25",
      "2026-06-29",
      "2026-06-30"
    ],
    "politics": [
      "2026-06-17",
      "2026-06-18",
      "2026-06-19",
      "2026-06-30"
    ],
    "movies": [
      "2026-06-17",
      "2026-06-18",
      "2026-06-19",
      "2026-06-20",
      "2026-06-21",
      "2026-06-22",
      "2026-06-23",
      "2026-06-24",
      "2026-06-25",
      "2026-06-26",
      "2026-06-27",
      "2026-06-28",
      "2026-06-29"
    ],
    "nsfw": [
      "2026-06-17",
      "2026-06-18",
      "2026-06-19",
      "2026-06-20",
      "2026-06-21",
      "2026-06-22",
      "2026-06-23",
      "2026-06-24",
      "2026-06-25",
      "2026-06-30"
    ]
  }
}